setup.py
ah_probability/Binomialdistribution.py
ah_probability/Gaussiandistribution.py
ah_probability/Generaldistribution.py
ah_probability/__init__.py
ah_probability.egg-info/PKG-INFO
ah_probability.egg-info/SOURCES.txt
ah_probability.egg-info/dependency_links.txt
ah_probability.egg-info/not-zip-safe
ah_probability.egg-info/top_level.txt