Metadata-Version: 1.0
Name: ah-probability
Version: 0.1
Summary: Gaussian distributions
Home-page: UNKNOWN
Author: Aliaksandr Hryshchuk
Author-email: alex_grishchuk@tut.by
License: UNKNOWN
Platform: UNKNOWN
